wd_llm_caption/__init__.py
wd_llm_caption/caption.py
wd_llm_caption/gui.py
wd_llm_caption/configs/default_florence.json
wd_llm_caption/configs/default_joy.json
wd_llm_caption/configs/default_llama_3.2V.json
wd_llm_caption/configs/default_minicpm.json
wd_llm_caption/configs/default_qwen2_vl.json
wd_llm_caption/configs/default_wd.json
wd_llm_caption/utils/__init__.py
wd_llm_caption/utils/download.py
wd_llm_caption/utils/image.py
wd_llm_caption/utils/inference.py
wd_llm_caption/utils/logger.py
wd_llm_caption-0.1.4a0.dist-info/LICENSE
wd_llm_caption-0.1.4a0.dist-info/METADATA
wd_llm_caption-0.1.4a0.dist-info/WHEEL
wd_llm_caption-0.1.4a0.dist-info/entry_points.txt
wd_llm_caption-0.1.4a0.dist-info/top_level.txt
wd_llm_caption-0.1.4a0.dist-info/RECORD
