Metadata-Version: 2.1
Name: wd-llm-caption
Version: 0.1.4a0
Summary: A Python base cli tool for caption images with WD series, Joy-caption-pre-alpha, meta Llama 3.2 Vision Instruct, Qwen2 VL Instruct, Mini-CPM V2.6 and Florence-2 models.
Author-email: DukeG <fireicewolf@gmail.com>
License: Apache License
Project-URL: Homepage, https://github.com/fireicewolf/wd-llm-caption-cli
Project-URL: Issues, https://github.com/fireicewolf/wd-llm-caption-cli/issues
Keywords: Image Caption,WD,Llama 3.2 Vision Instruct,Joy Caption Alpha,Qwen2 VL Instruct,Mini-CPM V2.6,Florence-2
Classifier: Development Status :: 3 - Alpha
Classifier: Intended Audience :: Developers
Classifier: Intended Audience :: Science/Research
Classifier: License :: OSI Approved :: Apache Software License
Classifier: Operating System :: OS Independent
Classifier: Programming Language :: Python :: 3.10
Classifier: Topic :: Scientific/Engineering :: Artificial Intelligence
Requires-Python: >=3.10
License-File: LICENSE
Requires-Dist: numpy<2.0.0,>=1.26.4
Requires-Dist: opencv-python-headless==4.10.0.84
Requires-Dist: pillow>=10.4.0
Requires-Dist: requests==2.32.3
Requires-Dist: tqdm==4.66.5
Requires-Dist: accelerate>=0.34.2
Requires-Dist: bitsandbytes>=0.42.0
Requires-Dist: sentencepiece==0.2.0
Requires-Dist: transformers==4.45.2
Requires-Dist: timm==1.0.11
Requires-Dist: torch>=2.1.0
Requires-Dist: onnx==1.17.0
Requires-Dist: onnxruntime==1.19.2
Requires-Dist: huggingface-hub>=0.26.0
Requires-Dist: modelscope>=1.19.0
Requires-Dist: gradio>=5.1.0
